pyqsim/__init__.py
pyqsim/bitgate.py
pyqsim/core.py
pyqsim/gates.py
pyqsim/operations.py
pyqsim/qubit.py
pyqsim/reggate.py
pyqsim/types.py
pyqsim-0.0.4.dist-info/METADATA
pyqsim-0.0.4.dist-info/WHEEL
pyqsim-0.0.4.dist-info/top_level.txt
pyqsim-0.0.4.dist-info/RECORD
